odoo/addons/company_sanitary_registry/README.rst
odoo/addons/company_sanitary_registry/__init__.py
odoo/addons/company_sanitary_registry/__manifest__.py
odoo/addons/company_sanitary_registry/i18n/company_sanitary_registry.pot
odoo/addons/company_sanitary_registry/i18n/es.po
odoo/addons/company_sanitary_registry/i18n/it.po
odoo/addons/company_sanitary_registry/models/__init__.py
odoo/addons/company_sanitary_registry/models/res_company.py
odoo/addons/company_sanitary_registry/readme/CONTRIBUTORS.md
odoo/addons/company_sanitary_registry/readme/DESCRIPTION.md
odoo/addons/company_sanitary_registry/static/description/icon.png
odoo/addons/company_sanitary_registry/static/description/index.html
odoo/addons/company_sanitary_registry/templates/sanitary_registry_template.xml
odoo/addons/company_sanitary_registry/views/res_company_view.xml
odoo_addon_company_sanitary_registry-18.0.1.0.0.2.dist-info/METADATA
odoo_addon_company_sanitary_registry-18.0.1.0.0.2.dist-info/WHEEL
odoo_addon_company_sanitary_registry-18.0.1.0.0.2.dist-info/top_level.txt
odoo_addon_company_sanitary_registry-18.0.1.0.0.2.dist-info/RECORD
